inputer/__init__.py
inputer/inputer.py
inputer-0.0.2.dist-info/METADATA
inputer-0.0.2.dist-info/WHEEL
inputer-0.0.2.dist-info/top_level.txt
inputer-0.0.2.dist-info/RECORD
