Metadata-Version: 2.1
Name: inputer
Version: 0.0.2
Summary: Print before input
Home-page: https://github.com/Time-Coder/inputer
Author: Time-Coder
Author-email: binghui.wang@foxmail.com
License: UNKNOWN
Platform: UNKNOWN
Classifier: Programming Language :: Python :: 3
Classifier: License :: OSI Approved :: MIT License
Classifier: Operating System :: OS Independent
Requires-Dist: click
